{"invalidated":[{"elements":{"name":"canvas","type":"canvas","controlType":"canvas","containerOrder":"important","children":[{"name":"_v3fo93c13","id":"_2dp872lb7","type":"text","importance":"normal","order":-1,"orig_width":106,"orig_height":28,"item":false,"typed":false,"alternate":false,"x":4,"y":16,"width":172,"height":45,"left_column":1,"right_column":1,"canvas_alignment":0,"canvas_child":true,"size_factor":0,"size_combo":[172,45,0]},{"name":"_lgk2vsxij","id":"_skl3rwlg3","type":"text","importance":"normal","order":-1,"orig_width":118,"orig_height":13,"item":false,"typed":false,"alternate":false,"x":4,"y":80,"width":172,"height":18,"left_column":1,"right_column":1,"canvas_alignment":0,"canvas_child":true,"size_factor":0,"size_combo":[172,18,0]},{"name":"_yhk6rggvl","id":"_hd7wffosp","type":"separator","importance":"normal","order":-1,"orig_width":292,"orig_height":4,"item":false,"typed":false,"alternate":false,"x":4,"y":112,"width":172,"height":4,"left_column":1,"right_column":1,"canvas_alignment":0,"canvas_child":true,"size_factor":0,"size_combo":[172,4,0]},{"name":"_bhro0f2x9","id":"alternate","type":"group","importance":"normal","containerOrder":"unimportant","order":-1,"orig_width":173,"orig_height":46.5,"item":false,"typed":false,"alternate":"_hodjmdlfh","children":[],"representations":["_duurj8x7u","_hodjmdlfh","_ixeaqjz98"],"alternate_width":67,"alternate_height":67,"x":184,"y":16,"width":172,"height":172,"left_column":2,"right_column":2,"canvas_alignment":2,"canvas_child":true,"size_factor":0,"size_combo":[172,172,0]},{"name":"_scmfxonz7","id":"group","type":"group","importance":"normal","containerOrder":"unimportant","order":-1,"orig_width":173,"orig_height":46.5,"item":false,"typed":false,"alternate":false,"children":[{"name":"_pvykyhl3g","id":"_bnl9006jo","type":"text","importance":"normal","order":-1,"orig_width":87,"orig_height":41,"item":false,"typed":false,"alternate":false,"x":61,"y":240,"width":238,"height":112,"size_factor":4,"size_combo":[238,112,4]},{"name":"_16rtdzppj","id":"_jeb2tqdfh","type":"text","importance":"normal","order":-1,"orig_width":75,"orig_height":25,"item":false,"typed":false,"alternate":false,"x":36,"y":356,"width":288,"height":96,"size_factor":4,"size_combo":[288,96,4]}],"x":4,"y":240,"width":352,"height":212,"left_column":1,"right_column":2,"canvas_alignment":0,"canvas_child":true,"arrangement":1,"alignment":1,"padding":4},{"name":"_x2xxpf3j1","id":"_2uz7acrpw","type":"text","importance":"normal","order":-1,"orig_width":203,"orig_height":14,"item":false,"typed":false,"alternate":false,"x":4,"y":464,"width":352,"height":24,"left_column":1,"right_column":2,"canvas_alignment":2,"canvas_child":true,"size_factor":0,"size_combo":[352,24,0]},{"name":"_mp3me4nlp","id":"group","type":"group","importance":"normal","containerOrder":"unimportant","order":-1,"orig_width":173,"orig_height":46.5,"item":false,"typed":true,"alternate":false,"children":[{"name":"_4jjl82s2c","id":"item","type":"group","importance":"normal","containerOrder":"unimportant","order":-1,"orig_width":173,"orig_height":46.5,"item":true,"typed":false,"alternate":false,"children":[{"name":"_aj7hty7fl","id":"_o2p5nwbpn","type":"text","importance":"normal","order":-1,"orig_width":52,"orig_height":20,"item":false,"typed":false,"alternate":false,"correspondingIDs":["_16eumqe1k","_wixqpvdou"],"x":9,"y":544,"width":42,"height":16,"size_factor":0,"size_combo":[42,16,0]},{"name":"_fo0tt5ngc","id":"_823cxxf8n","type":"icon","importance":"normal","order":-1,"orig_width":48,"orig_height":48,"item":false,"typed":false,"alternate":false,"correspondingIDs":["_b3m5yn86x","_c983cl65m"],"x":6,"y":564,"width":48,"height":48,"size_factor":0,"size_combo":[48,48,0]}],"x":6,"y":544,"width":48,"height":68,"arrangement":1,"alignment":1,"padding":4},{"name":"_wlp33tz5m","id":"item","type":"group","importance":"normal","containerOrder":"unimportant","order":-1,"orig_width":173,"orig_height":46.5,"item":true,"typed":false,"alternate":false,"children":[{"name":"_16eumqe1k","id":"_j5bxu3rel","type":"text","importance":"normal","order":-1,"orig_width":52,"orig_height":20,"item":false,"typed":false,"alternate":false,"correspondingIDs":["_aj7hty7fl","_wixqpvdou"],"x":69,"y":544,"width":42,"height":16,"size_factor":0,"size_combo":[42,16,0]},{"name":"_b3m5yn86x","id":"_600na4kt1","type":"icon","importance":"normal","order":-1,"orig_width":48,"orig_height":48,"item":false,"typed":false,"alternate":false,"correspondingIDs":["_fo0tt5ngc","_c983cl65m"],"x":66,"y":564,"width":48,"height":48,"size_factor":0,"size_combo":[48,48,0]}],"x":66,"y":544,"width":48,"height":68,"arrangement":1,"alignment":1,"padding":4},{"name":"_dn1e3gbp6","id":"item","type":"group","importance":"normal","containerOrder":"unimportant","order":-1,"orig_width":173,"orig_height":46.5,"item":true,"typed":false,"alternate":false,"children":[{"name":"_wixqpvdou","id":"_8k3non8dv","type":"text","importance":"normal","order":-1,"orig_width":52,"orig_height":20,"item":false,"typed":false,"alternate":false,"correspondingIDs":["_aj7hty7fl","_16eumqe1k"],"x":129,"y":544,"width":42,"height":16,"size_factor":0,"size_combo":[42,16,0]},{"name":"_c983cl65m","id":"_bty2gwq41","type":"icon","importance":"normal","order":-1,"orig_width":48,"orig_height":48,"item":false,"typed":false,"alternate":false,"correspondingIDs":["_fo0tt5ngc","_b3m5yn86x"],"x":126,"y":564,"width":48,"height":48,"size_factor":0,"size_combo":[48,48,0]}],"x":126,"y":544,"width":48,"height":68,"arrangement":1,"alignment":1,"padding":4}],"x":4,"y":544,"width":172,"height":68,"left_column":1,"right_column":1,"canvas_alignment":0,"canvas_child":true,"arrangement":0,"alignment":1,"padding":12}],"orig_width":173,"orig_height":46.5,"x":0,"y":0,"margin":4,"baseline_grid":16,"columns":2,"column_width":172,"gutter_width":8,"grid_layout":[4,2,8,172]},"id":"46c516a88f2e401ea3ebb052ba754093","cost":3.374604015770587,"valid":true,"saved":0,"conflicts":[{"type":"prevent","shapeID":"_scmfxonz7","variable":"padding","value":4}],"new":false,"invalidated":true},{"elements":{"name":"canvas","type":"canvas","controlType":"canvas","containerOrder":"important","children":[{"name":"_v3fo93c13","id":"_2dp872lb7","type":"text","importance":"normal","order":-1,"orig_width":106,"orig_height":28,"item":false,"typed":false,"alternate":false,"x":248,"y":20,"width":104,"height":27,"left_column":3,"right_column":3,"canvas_alignment":2,"canvas_child":true,"size_factor":0,"size_combo":[104,27,0]},{"name":"_lgk2vsxij","id":"_skl3rwlg3","type":"text","importance":"normal","order":-1,"orig_width":118,"orig_height":13,"item":false,"typed":false,"alternate":false,"x":128,"y":68,"width":224,"height":24,"left_column":2,"right_column":3,"canvas_alignment":2,"canvas_child":true,"size_factor":0,"size_combo":[224,24,0]},{"name":"_yhk6rggvl","id":"_hd7wffosp","type":"separator","importance":"normal","order":-1,"orig_width":292,"orig_height":4,"item":false,"typed":false,"alternate":false,"x":128,"y":116,"width":224,"height":4,"left_column":2,"right_column":3,"canvas_alignment":2,"canvas_child":true,"size_factor":0,"size_combo":[224,4,0]},{"name":"_bhro0f2x9","id":"alternate","type":"group","importance":"normal","containerOrder":"unimportant","order":-1,"orig_width":173,"orig_height":46.5,"item":false,"typed":false,"alternate":"_duurj8x7u","children":[],"representations":["_duurj8x7u","_hodjmdlfh","_ixeaqjz98"],"alternate_width":67,"alternate_height":67,"x":8,"y":52,"width":104,"height":104,"left_column":1,"right_column":1,"canvas_alignment":0,"canvas_child":true,"size_factor":0,"size_combo":[104,104,0]},{"name":"_scmfxonz7","id":"group","type":"group","importance":"normal","containerOrder":"unimportant","order":-1,"orig_width":173,"orig_height":46.5,"item":false,"typed":false,"alternate":false,"children":[{"name":"_pvykyhl3g","id":"_bnl9006jo","type":"text","importance":"normal","order":-1,"orig_width":87,"orig_height":41,"item":false,"typed":false,"alternate":false,"x":129,"y":132,"width":110,"height":52,"size_factor":3,"size_combo":[110,52,3]},{"name":"_16rtdzppj","id":"_jeb2tqdfh","type":"text","importance":"normal","order":-1,"orig_width":75,"orig_height":25,"item":false,"typed":false,"alternate":false,"x":243,"y":148,"width":108,"height":36,"size_factor":3,"size_combo":[108,36,3]}],"x":128,"y":132,"width":224,"height":52,"left_column":2,"right_column":3,"canvas_alignment":2,"canvas_child":true,"arrangement":0,"alignment":2,"padding":4},{"name":"_x2xxpf3j1","id":"_2uz7acrpw","type":"text","importance":"normal","order":-1,"orig_width":203,"orig_height":14,"item":false,"typed":false,"alternate":false,"x":8,"y":204,"width":344,"height":23,"left_column":1,"right_column":3,"canvas_alignment":1,"canvas_child":true,"size_factor":0,"size_combo":[344,23,0]},{"name":"_mp3me4nlp","id":"group","type":"group","importance":"normal","containerOrder":"unimportant","order":-1,"orig_width":173,"orig_height":46.5,"item":false,"typed":true,"alternate":false,"children":[{"name":"_4jjl82s2c","id":"item","type":"group","importance":"normal","containerOrder":"unimportant","order":-1,"orig_width":173,"orig_height":46.5,"item":true,"typed":false,"alternate":false,"children":[{"name":"_aj7hty7fl","id":"_o2p5nwbpn","type":"text","importance":"normal","order":-1,"orig_width":52,"orig_height":20,"item":false,"typed":false,"alternate":false,"correspondingIDs":["_16eumqe1k","_wixqpvdou"],"x":150,"y":440,"width":176,"height":68,"size_factor":12,"size_combo":[176,68,12]},{"name":"_fo0tt5ngc","id":"_823cxxf8n","type":"icon","importance":"normal","order":-1,"orig_width":48,"orig_height":48,"item":false,"typed":false,"alternate":false,"correspondingIDs":["_b3m5yn86x","_c983cl65m"],"x":34,"y":412,"width":96,"height":96,"size_factor":12,"size_combo":[96,96,12]}],"x":34,"y":412,"width":292,"height":96,"arrangement":0,"alignment":2,"padding":20},{"name":"_wlp33tz5m","id":"item","type":"group","importance":"normal","containerOrder":"unimportant","order":-1,"orig_width":173,"orig_height":46.5,"item":true,"typed":false,"alternate":false,"children":[{"name":"_16eumqe1k","id":"_j5bxu3rel","type":"text","importance":"normal","order":-1,"orig_width":52,"orig_height":20,"item":false,"typed":false,"alternate":false,"correspondingIDs":["_aj7hty7fl","_wixqpvdou"],"x":150,"y":316,"width":176,"height":68,"size_factor":12,"size_combo":[176,68,12]},{"name":"_b3m5yn86x","id":"_600na4kt1","type":"icon","importance":"normal","order":-1,"orig_width":48,"orig_height":48,"item":false,"typed":false,"alternate":false,"correspondingIDs":["_fo0tt5ngc","_c983cl65m"],"x":34,"y":288,"width":96,"height":96,"size_factor":12,"size_combo":[96,96,12]}],"x":34,"y":288,"width":292,"height":96,"arrangement":0,"alignment":2,"padding":20},{"name":"_dn1e3gbp6","id":"item","type":"group","importance":"normal","containerOrder":"unimportant","order":-1,"orig_width":173,"orig_height":46.5,"item":true,"typed":false,"alternate":false,"children":[{"name":"_wixqpvdou","id":"_8k3non8dv","type":"text","importance":"normal","order":-1,"orig_width":52,"orig_height":20,"item":false,"typed":false,"alternate":false,"correspondingIDs":["_aj7hty7fl","_16eumqe1k"],"x":150,"y":564,"width":176,"height":68,"size_factor":12,"size_combo":[176,68,12]},{"name":"_c983cl65m","id":"_bty2gwq41","type":"icon","importance":"normal","order":-1,"orig_width":48,"orig_height":48,"item":false,"typed":false,"alternate":false,"correspondingIDs":["_fo0tt5ngc","_b3m5yn86x"],"x":34,"y":536,"width":96,"height":96,"size_factor":12,"size_combo":[96,96,12]}],"x":34,"y":536,"width":292,"height":96,"arrangement":0,"alignment":2,"padding":20}],"x":8,"y":288,"width":344,"height":344,"left_column":1,"right_column":3,"canvas_alignment":2,"canvas_child":true,"arrangement":1,"alignment":2,"padding":28}],"orig_width":173,"orig_height":46.5,"x":0,"y":0,"margin":8,"baseline_grid":4,"columns":3,"column_width":104,"gutter_width":16,"grid_layout":[8,3,16,104]},"id":"7d681b91d9a347fa8f68efa9975e0a60","cost":3.961384046251475,"valid":true,"saved":0,"conflicts":[{"type":"prevent","shapeID":"_scmfxonz7","variable":"padding","value":4}],"new":false,"invalidated":true},{"elements":{"name":"canvas","type":"canvas","controlType":"canvas","containerOrder":"unimportant","children":[{"name":"_v3fo93c13","id":"_2dp872lb7","type":"text","importance":"normal","order":-1,"orig_width":106,"orig_height":28,"item":false,"typed":false,"alternate":false,"x":236,"y":384,"width":96,"height":25,"left_column":3,"right_column":3,"canvas_alignment":2,"canvas_child":true,"size_factor":0,"size_combo":[96,25,0]},{"name":"_lgk2vsxij","id":"_skl3rwlg3","type":"text","importance":"normal","order":-1,"orig_width":118,"orig_height":13,"item":false,"typed":false,"alternate":false,"x":28,"y":336,"width":304,"height":33,"left_column":1,"right_column":3,"canvas_alignment":1,"canvas_child":true,"size_factor":1,"size_combo":[304,33,1]},{"name":"_yhk6rggvl","id":"_hd7wffosp","type":"separator","importance":"normal","order":-1,"orig_width":292,"orig_height":4,"item":false,"typed":false,"alternate":false,"x":132,"y":464,"width":200,"height":4,"left_column":2,"right_column":3,"canvas_alignment":2,"canvas_child":true,"size_factor":0,"size_combo":[200,4,0]},{"name":"_bhro0f2x9","id":"alternate","type":"group","importance":"normal","containerOrder":"unimportant","order":-1,"orig_width":173,"orig_height":46.5,"item":false,"typed":false,"alternate":"_hodjmdlfh","children":[],"representations":["_duurj8x7u","_hodjmdlfh","_ixeaqjz98"],"alternate_width":67,"alternate_height":67,"x":28,"y":376,"width":96,"height":96,"left_column":1,"right_column":1,"canvas_alignment":0,"canvas_child":true,"size_factor":0,"size_combo":[96,96,0]},{"name":"_scmfxonz7","id":"group","type":"group","importance":"normal","containerOrder":"unimportant","order":-1,"orig_width":173,"orig_height":46.5,"item":false,"typed":false,"alternate":false,"children":[{"name":"_pvykyhl3g","id":"_bnl9006jo","type":"text","importance":"normal","order":-1,"orig_width":87,"orig_height":41,"item":false,"typed":false,"alternate":false,"x":70,"y":512,"width":118,"height":56,"size_factor":2,"size_combo":[118,56,2]},{"name":"_16rtdzppj","id":"_jeb2tqdfh","type":"text","importance":"normal","order":-1,"orig_width":75,"orig_height":25,"item":false,"typed":false,"alternate":false,"x":68,"y":572,"width":120,"height":40,"size_factor":2,"size_combo":[120,40,2]}],"x":28,"y":512,"width":200,"height":100,"left_column":1,"right_column":2,"canvas_alignment":0,"canvas_child":true,"arrangement":1,"alignment":2,"padding":4},{"name":"_x2xxpf3j1","id":"_2uz7acrpw","type":"text","importance":"normal","order":-1,"orig_width":203,"orig_height":14,"item":false,"typed":false,"alternate":false,"x":28,"y":480,"width":304,"height":20,"left_column":1,"right_column":3,"canvas_alignment":1,"canvas_child":true,"size_factor":0,"size_combo":[304,20,0]},{"name":"_mp3me4nlp","id":"group","type":"group","importance":"normal","containerOrder":"unimportant","order":-1,"orig_width":173,"orig_height":46.5,"item":false,"typed":true,"alternate":false,"children":[{"name":"_4jjl82s2c","id":"item","type":"group","importance":"normal","containerOrder":"unimportant","order":-1,"orig_width":173,"orig_height":46.5,"item":true,"typed":false,"alternate":false,"children":[{"name":"_aj7hty7fl","id":"_o2p5nwbpn","type":"text","importance":"normal","order":-1,"orig_width":52,"orig_height":20,"item":false,"typed":false,"alternate":false,"correspondingIDs":["_16eumqe1k","_wixqpvdou"],"x":153,"y":240,"width":146,"height":56,"size_factor":5,"size_combo":[146,56,5]},{"name":"_fo0tt5ngc","id":"_823cxxf8n","type":"icon","importance":"normal","order":-1,"orig_width":48,"orig_height":48,"item":false,"typed":false,"alternate":false,"correspondingIDs":["_b3m5yn86x","_c983cl65m"],"x":61,"y":224,"width":88,"height":88,"size_factor":5,"size_combo":[88,88,5]}],"x":61,"y":224,"width":238,"height":88,"arrangement":0,"alignment":1,"padding":4},{"name":"_wlp33tz5m","id":"item","type":"group","importance":"normal","containerOrder":"unimportant","order":-1,"orig_width":173,"orig_height":46.5,"item":true,"typed":false,"alternate":false,"children":[{"name":"_16eumqe1k","id":"_j5bxu3rel","type":"text","importance":"normal","order":-1,"orig_width":52,"orig_height":20,"item":false,"typed":false,"alternate":false,"correspondingIDs":["_aj7hty7fl","_wixqpvdou"],"x":153,"y":144,"width":146,"height":56,"size_factor":5,"size_combo":[146,56,5]},{"name":"_b3m5yn86x","id":"_600na4kt1","type":"icon","importance":"normal","order":-1,"orig_width":48,"orig_height":48,"item":false,"typed":false,"alternate":false,"correspondingIDs":["_fo0tt5ngc","_c983cl65m"],"x":61,"y":128,"width":88,"height":88,"size_factor":5,"size_combo":[88,88,5]}],"x":61,"y":128,"width":238,"height":88,"arrangement":0,"alignment":1,"padding":4},{"name":"_dn1e3gbp6","id":"item","type":"group","importance":"normal","containerOrder":"unimportant","order":-1,"orig_width":173,"orig_height":46.5,"item":true,"typed":false,"alternate":false,"children":[{"name":"_wixqpvdou","id":"_8k3non8dv","type":"text","importance":"normal","order":-1,"orig_width":52,"orig_height":20,"item":false,"typed":false,"alternate":false,"correspondingIDs":["_aj7hty7fl","_16eumqe1k"],"x":153,"y":48,"width":146,"height":56,"size_factor":5,"size_combo":[146,56,5]},{"name":"_c983cl65m","id":"_bty2gwq41","type":"icon","importance":"normal","order":-1,"orig_width":48,"orig_height":48,"item":false,"typed":false,"alternate":false,"correspondingIDs":["_fo0tt5ngc","_b3m5yn86x"],"x":61,"y":32,"width":88,"height":88,"size_factor":5,"size_combo":[88,88,5]}],"x":61,"y":32,"width":238,"height":88,"arrangement":0,"alignment":1,"padding":4}],"x":28,"y":32,"width":304,"height":280,"left_column":1,"right_column":3,"canvas_alignment":0,"canvas_child":true,"arrangement":1,"alignment":2,"padding":8}],"orig_width":173,"orig_height":46.5,"x":0,"y":0,"margin":28,"baseline_grid":8,"columns":3,"column_width":96,"gutter_width":8,"grid_layout":[28,3,8,96]},"id":"943639b3f222422a9f50ef23512afb9e","cost":3.7361719601861507,"valid":true,"saved":0,"conflicts":[{"type":"prevent","shapeID":"_scmfxonz7","variable":"padding","value":4}],"new":false,"invalidated":true},{"elements":{"name":"canvas","type":"canvas","controlType":"canvas","containerOrder":"unimportant","children":[{"name":"_v3fo93c13","id":"_2dp872lb7","type":"text","importance":"normal","order":-1,"orig_width":106,"orig_height":28,"item":false,"typed":false,"alternate":false,"x":24,"y":240,"width":312,"height":82,"left_column":1,"right_column":2,"canvas_alignment":2,"canvas_child":true,"size_factor":1,"size_combo":[312,82,1]},{"name":"_lgk2vsxij","id":"_skl3rwlg3","type":"text","importance":"normal","order":-1,"orig_width":118,"orig_height":13,"item":false,"typed":false,"alternate":false,"x":188,"y":512,"width":148,"height":16,"left_column":2,"right_column":2,"canvas_alignment":2,"canvas_child":true,"size_factor":0,"size_combo":[148,16,0]},{"name":"_yhk6rggvl","id":"_hd7wffosp","type":"separator","importance":"normal","order":-1,"orig_width":292,"orig_height":4,"item":false,"typed":false,"alternate":false,"x":24,"y":208,"width":312,"height":4,"left_column":1,"right_column":2,"canvas_alignment":0,"canvas_child":true,"size_factor":1,"size_combo":[312,4,1]},{"name":"_bhro0f2x9","id":"alternate","type":"group","importance":"normal","containerOrder":"unimportant","order":-1,"orig_width":173,"orig_height":46.5,"item":false,"typed":false,"alternate":"_duurj8x7u","children":[],"representations":["_duurj8x7u","_hodjmdlfh","_ixeaqjz98"],"alternate_width":67,"alternate_height":67,"x":24,"y":368,"width":148,"height":148,"left_column":1,"right_column":1,"canvas_alignment":0,"canvas_child":true,"size_factor":0,"size_combo":[148,148,0]},{"name":"_scmfxonz7","id":"group","type":"group","importance":"normal","containerOrder":"unimportant","order":-1,"orig_width":173,"orig_height":46.5,"item":false,"typed":false,"alternate":false,"children":[{"name":"_pvykyhl3g","id":"_bnl9006jo","type":"text","importance":"normal","order":-1,"orig_width":87,"orig_height":41,"item":false,"typed":false,"alternate":false,"x":186,"y":544,"width":136,"height":64,"size_factor":1,"size_combo":[136,64,1]},{"name":"_16rtdzppj","id":"_jeb2tqdfh","type":"text","importance":"normal","order":-1,"orig_width":75,"orig_height":25,"item":false,"typed":false,"alternate":false,"x":38,"y":560,"width":144,"height":48,"size_factor":1,"size_combo":[144,48,1]}],"x":24,"y":544,"width":312,"height":64,"left_column":1,"right_column":2,"canvas_alignment":0,"canvas_child":true,"arrangement":0,"alignment":2,"padding":4},{"name":"_x2xxpf3j1","id":"_2uz7acrpw","type":"text","importance":"normal","order":-1,"orig_width":203,"orig_height":14,"item":false,"typed":false,"alternate":false,"x":24,"y":336,"width":312,"height":21,"left_column":1,"right_column":2,"canvas_alignment":1,"canvas_child":true,"size_factor":0,"size_combo":[312,21,0]},{"name":"_mp3me4nlp","id":"group","type":"group","importance":"normal","containerOrder":"unimportant","order":-1,"orig_width":173,"orig_height":46.5,"item":false,"typed":true,"alternate":false,"children":[{"name":"_4jjl82s2c","id":"item","type":"group","importance":"normal","containerOrder":"unimportant","order":-1,"orig_width":173,"orig_height":46.5,"item":true,"typed":false,"alternate":false,"children":[{"name":"_aj7hty7fl","id":"_o2p5nwbpn","type":"text","importance":"normal","order":-1,"orig_width":52,"orig_height":20,"item":false,"typed":false,"alternate":false,"correspondingIDs":["_16eumqe1k","_wixqpvdou"],"x":29,"y":104,"width":82,"height":32,"size_factor":1,"size_combo":[82,32,1]},{"name":"_fo0tt5ngc","id":"_823cxxf8n","type":"icon","importance":"normal","order":-1,"orig_width":48,"orig_height":48,"item":false,"typed":false,"alternate":false,"correspondingIDs":["_b3m5yn86x","_c983cl65m"],"x":29,"y":32,"width":64,"height":64,"size_factor":1,"size_combo":[64,64,1]}],"x":29,"y":32,"width":82,"height":104,"arrangement":1,"alignment":0,"padding":8},{"name":"_wlp33tz5m","id":"item","type":"group","importance":"normal","containerOrder":"unimportant","order":-1,"orig_width":173,"orig_height":46.5,"item":true,"typed":false,"alternate":false,"children":[{"name":"_16eumqe1k","id":"_j5bxu3rel","type":"text","importance":"normal","order":-1,"orig_width":52,"orig_height":20,"item":false,"typed":false,"alternate":false,"correspondingIDs":["_aj7hty7fl","_wixqpvdou"],"x":139,"y":104,"width":82,"height":32,"size_factor":1,"size_combo":[82,32,1]},{"name":"_b3m5yn86x","id":"_600na4kt1","type":"icon","importance":"normal","order":-1,"orig_width":48,"orig_height":48,"item":false,"typed":false,"alternate":false,"correspondingIDs":["_fo0tt5ngc","_c983cl65m"],"x":139,"y":32,"width":64,"height":64,"size_factor":1,"size_combo":[64,64,1]}],"x":139,"y":32,"width":82,"height":104,"arrangement":1,"alignment":0,"padding":8},{"name":"_dn1e3gbp6","id":"item","type":"group","importance":"normal","containerOrder":"unimportant","order":-1,"orig_width":173,"orig_height":46.5,"item":true,"typed":false,"alternate":false,"children":[{"name":"_wixqpvdou","id":"_8k3non8dv","type":"text","importance":"normal","order":-1,"orig_width":52,"orig_height":20,"item":false,"typed":false,"alternate":false,"correspondingIDs":["_aj7hty7fl","_16eumqe1k"],"x":249,"y":104,"width":82,"height":32,"size_factor":1,"size_combo":[82,32,1]},{"name":"_c983cl65m","id":"_bty2gwq41","type":"icon","importance":"normal","order":-1,"orig_width":48,"orig_height":48,"item":false,"typed":false,"alternate":false,"correspondingIDs":["_fo0tt5ngc","_b3m5yn86x"],"x":249,"y":32,"width":64,"height":64,"size_factor":1,"size_combo":[64,64,1]}],"x":249,"y":32,"width":82,"height":104,"arrangement":1,"alignment":0,"padding":8}],"x":24,"y":32,"width":312,"height":104,"left_column":1,"right_column":2,"canvas_alignment":2,"canvas_child":true,"arrangement":0,"alignment":0,"padding":28}],"orig_width":173,"orig_height":46.5,"x":0,"y":0,"margin":24,"baseline_grid":16,"columns":2,"column_width":148,"gutter_width":16,"grid_layout":[24,2,16,148]},"id":"0445498b809d4d658f8f6b4dfc2de7bd","cost":3.691020719230036,"valid":true,"saved":0,"conflicts":[{"type":"prevent","shapeID":"_scmfxonz7","variable":"padding","value":4}],"new":false,"invalidated":true}]}